[
  {
    "country": "Tokyo",

    "Flight duration": "12h 26m",
    "Distance": "9605km",
    "gCO₂ per passenger": "1355kg",

    "Google search": 6776325,
    "Tweet": 6776325,
    "Spam": 4517550,
    "E-Mail": 338816,
    "AI prompt": 315178,
    "E-Mail attachment": 27105,
    "Streaming": 13553,
    "Video conference": 9035
  },
  {
    "country": "New York",

    "Flight duration": "8h 23m",
    "Distance": "6342km",
    "gCO₂ per passenger": "895kg",

    "Google search": 4474280,
    "Tweet": 4474280,
    "Spam": 2982853,
    "E-Mail": 223714,
    "AI prompt": 208106,
    "E-Mail attachment": 17897,
    "Streaming": 8948,
    "Video conference": 5965
  },
  {
    "country": "Berlin",

    "Flight duration": "1h 20m",
    "Distance": "670km",
    "gCO₂ per passenger": "95kg",

    "Google search": 472695,
    "Tweet": 472695,
    "Spam": 315123,
    "E-Mail": 23634,
    "AI prompt": 21985,
    "E-Mail attachment": 1890,
    "Streaming": 945,
    "Video conference": 630
  },  
  {
    "country": "Istanbul",

    "Flight duration": "2h 42m",
    "Distance": "1771km",
    "gCO₂ per passenger": "250kg",

    "Google search": 1249440,
    "Tweet": 1249440,
    "Spam": 832960,
    "E-Mail": 62472,
    "AI prompt": 58113,
    "E-Mail attachment": 4997,
    "Streaming": 2498,
    "Video conference": 1665
  },  
  {
    "country": "Barcelona",

    "Flight duration": "1h 32m",
    "Distance": "836km",
    "gCO₂ per passenger": "120kg",

    "Google search": 599795,
    "Tweet":  599795,
    "Spam": 399863,
    "E-Mail": 29990,
    "AI prompt": 27897,
    "E-Mail attachment": 2399,
    "Streaming": 1199,
    "Video conference": 800
  },  
  {
    "country": "Dubai",

    "Flight duration": "6h 25m",
    "Distance": "4767km",
    "gCO₂ per passenger": "673km",

    "Google search": 3363115,
    "Tweet": 3363115,
    "Spam": 2242076,
    "E-Mail": 168156,
    "AI prompt": 156424,
    "E-Mail attachment": 13453,
    "Streaming": 6726,
    "Video conference": 4484
  },  
  {
    "country": "Singapore",

    "Flight duration": "13h 18m",
    "Distance": "10301km",
    "gCO₂ per passenger": "1454kg",

    "Google search": 7267355,
    "Tweet": 7267355,
    "Spam": 4844903,
    "E-Mail": 363368,
    "AI prompt": 338016,
    "E-Mail attachment": 29069,
    "Streaming": 14535,
    "Video conference": 9690
  },
  {
    "country": "Beijing",

    "Flight duration": "10h 27m",
    "Distance": "8003km",
    "gCO₂ per passenger": "1129kg",

    "Google search": 5646115,
    "Tweet": 5646115,
    "Spam": 3764076,
    "E-Mail": 282306,
    "AI prompt": 262610,
    "E-Mail attachment": 22585,
    "Streaming": 11292,
    "Video conference": 7528
  }
]